README
setup.cfg
setup.py
DistanceClassifier/DistanceClassifier.py
DistanceClassifier/__init__.py
DistanceClassifier/_version.py
DistanceClassifier.egg-info/PKG-INFO
DistanceClassifier.egg-info/SOURCES.txt
DistanceClassifier.egg-info/dependency_links.txt
DistanceClassifier.egg-info/entry_points.txt
DistanceClassifier.egg-info/requires.txt
DistanceClassifier.egg-info/top_level.txt
DistanceClassifier.egg-info/zip-safe